.version
MANIFEST.in
README.rst
setup.cfg
setup.py
tasktimer.py
tasktimer.egg-info/PKG-INFO
tasktimer.egg-info/SOURCES.txt
tasktimer.egg-info/dependency_links.txt
tasktimer.egg-info/requires.txt
tasktimer.egg-info/top_level.txt