Metadata-Version: 1.1
Name: tasktimer
Version: 1.0.4
Summary: Indicates progress during runtime, while keeping track of time consumed by user-defined tasks.
Home-page: https://github.com/sigvaldm/tasktimer.git
Author: Sigvald Marholm
Author-email: marholm@marebakken.com
License: LGPL
Platform: UNKNOWN
Classifier: Programming Language :: Python :: 2.7
Classifier: Programming Language :: Python :: 3.5
Classifier: Programming Language :: Python :: 3.6
Classifier: Programming Language :: Python :: 3.7
